Metadata-Version: 2.1
Name: power-nlp-1.3
Version: 1.3
Summary: power nlp1
Home-page: https://github.com/ExpertOfAI/power_nlp
Author: ExpertOfAI1
License: MIT
Classifier: Programming Language :: Python :: 3
Classifier: License :: OSI Approved :: MIT License
Classifier: Operating System :: OS Independent
Requires-Python: >=3.6
